maple_guard/__init__.py
maple_guard/constants.py
maple_guard/log.py
maple_guard/six.py
maple_guard/utils.py
maple_guard/client/__init__.py
maple_guard/client/client.py
maple_guard/server/__init__.py
maple_guard/server/blocker.py
maple_guard/server/rate_limiter.py
maple_guard/server/redis_extend.py
maple_guard/server/server.py
maple_guard-0.2.4.data/scripts/run_maple_guard.py
maple_guard-0.2.4.dist-info/LICENSE
maple_guard-0.2.4.dist-info/METADATA
maple_guard-0.2.4.dist-info/WHEEL
maple_guard-0.2.4.dist-info/top_level.txt
maple_guard-0.2.4.dist-info/RECORD
