Metadata-Version: 2.1
Name: maple-guard
Version: 0.2.4
Summary: maple guard
Home-page: https://github.com/dantezhu/maple_guard
Author: dantezhu
Author-email: dantezhu <zny2008@gmail.com>
License: BSD
Project-URL: Homepage, https://github.com/dantezhu/maple_guard
Platform: any
License-File: LICENSE
Requires-Dist: maple
Requires-Dist: redis
Requires-Dist: gevent
